prefect_jupyter/__init__.py
prefect_jupyter/_version.py
prefect_jupyter/notebook.py
prefect_jupyter-0.3.1.dist-info/LICENSE
prefect_jupyter-0.3.1.dist-info/METADATA
prefect_jupyter-0.3.1.dist-info/WHEEL
prefect_jupyter-0.3.1.dist-info/top_level.txt
prefect_jupyter-0.3.1.dist-info/RECORD
